melodicious/__init__.py
melodicious/client.py
melodicious/playground.py
melodicious-0.0.1.dist-info/METADATA
melodicious-0.0.1.dist-info/WHEEL
melodicious-0.0.1.dist-info/top_level.txt
melodicious-0.0.1.dist-info/RECORD
