Metadata-Version: 2.1
Name: melodicious
Version: 0.0.1
Summary: A simple API client for AI-Music Generate
Home-page: https://github.com/cropsun/melodicious
Author: Cropsun
Author-email: melodiciousai@gmail.com
License: UNKNOWN
Platform: UNKNOWN
Classifier: Programming Language :: Python :: 3
Classifier: License :: OSI Approved :: MIT License
Classifier: Operating System :: OS Independent
Requires-Dist: requests
